cincodex.py
cincodex-0.1.0.dist-info/LICENSE
cincodex-0.1.0.dist-info/METADATA
cincodex-0.1.0.dist-info/WHEEL
cincodex-0.1.0.dist-info/RECORD
