Metadata-Version: 2.1
Name: cincodex
Version: 0.1.0
Summary: Simple, flexible, and unopinionated plugin system for Python projects.
Home-page: https://gitlab.com/ameily/cincodex
License: MIT
Keywords: plugin,pluggable,extension,extensible
Author: Adam Meily
Requires-Python: >=3.10,<4.0
Classifier: Development Status :: 4 - Beta
Classifier: Intended Audience :: Developers
Classifier: License :: OSI Approved :: MIT License
Classifier: Operating System :: MacOS
Classifier: Operating System :: Microsoft :: Windows
Classifier: Operating System :: POSIX
Classifier: Programming Language :: Python :: 3
Classifier: Programming Language :: Python :: 3.10
Classifier: Programming Language :: Python :: 3.11
Classifier: Topic :: Software Development :: Libraries
Project-URL: Documentation, https://cincodex.readthedocs.io/en/latest/
Project-URL: Repository, https://gitlab.com/ameily/cincodex
